tracy_blob_storage_client/__init__.py
tracy_blob_storage_client/aws_blob.py
tracy_blob_storage_client/azure_blob.py
tracy_blob_storage_client/base.py
tracy_blob_storage_client/factory.py
tracy_blob_storage_client-1.0.0.dist-info/METADATA
tracy_blob_storage_client-1.0.0.dist-info/WHEEL
tracy_blob_storage_client-1.0.0.dist-info/top_level.txt
tracy_blob_storage_client-1.0.0.dist-info/RECORD
